kisao/__init__.py
kisao/_version.py
kisao/core.py
kisao/data_model.py
kisao/exceptions.py
kisao/kisao.owl
kisao/utils.py
kisao/warnings.py
kisao-2.34.dist-info/LICENSE
kisao-2.34.dist-info/METADATA
kisao-2.34.dist-info/WHEEL
kisao-2.34.dist-info/top_level.txt
kisao-2.34.dist-info/RECORD
