Metadata-Version: 2.1
Name: kisao
Version: 2.34
Summary: Utilities for working with the Kinetic Simulation Algorithm Ontology (KiSAO)
Home-page: https://github.com/SED-ML/kisao
Author: SED-ML Editors
Author-email: sed-ml-editors@googlegroups.com
License: Apache 2.0
Download-URL: https://github.com/SED-ML/kisao
Keywords: systems biology,modeling,simulation,algorithm,ontology,KiSAO,SED-ML,SBML
Platform: UNKNOWN
Classifier: Development Status :: 3 - Alpha
Classifier: Intended Audience :: Science/Research
Classifier: License :: OSI Approved :: Apache Software License
Classifier: Topic :: Scientific/Engineering :: Bio-Informatics
Provides-Extra: substitutability-matrix
Provides-Extra: tests
Provides-Extra: docs
Provides-Extra: all
License-File: LICENSE
